Metadata-Version: 1.0
Name: gdb-probability
Version: 1.0
Summary: Gaussian and Binomial Distributions
Home-page: UNKNOWN
Author: Mayor Onyebueke
Author-email: mayoronyebueke@email.com
License: UNKNOWN
Platform: UNKNOWN
